LICENSE
pyclinic/__init__.py
pyclinic/base.py
pyclinic/cli.py
pyclinic/model_parser.py
pyclinic/models/openapi_model.py
pyclinic/models/postman_collection_model.py
pyclinic/models/postman_variables_model.py
pyclinic/models/swagger2.py
pyclinic/normalize.py
pyclinic/openapi.py
pyclinic/postman.py
pyclinic/swagger.py
pyclinic-0.3.3.dist-info/entry_points.txt
pyclinic-0.3.3.dist-info/LICENSE
pyclinic-0.3.3.dist-info/WHEEL
pyclinic-0.3.3.dist-info/METADATA
pyclinic-0.3.3.dist-info/RECORD
