Metadata-Version: 2.1
Name: pyclinic
Version: 0.3.3
Summary: A python library to test services like RESTful APIs
Home-page: https://github.com/ElSnoMan/pyclinic
License: MIT
Keywords: restful,api,testing,postman
Author: Carlos Kidman
Author-email: carlos@qap.dev
Requires-Python: >=3.7.1,<4.0.0
Classifier: License :: OSI Approved :: MIT License
Classifier: Programming Language :: Python :: 3
Classifier: Programming Language :: Python :: 3.8
Classifier: Programming Language :: Python :: 3.9
Requires-Dist: click (>=8.0.1,<9.0.0)
Requires-Dist: datamodel-code-generator (>=0.11.8,<0.12.0)
Requires-Dist: jsonpath-ng (>=1.5.3,<2.0.0)
Requires-Dist: pydantic (>=1.8.2,<2.0.0)
Requires-Dist: requests (>=2.26.0,<3.0.0)
Requires-Dist: rich (>=10.7.0,<11.0.0)
Project-URL: Repository, https://github.com/ElSnoMan/pyclinic
